lektor_tinymce.py
lektor_tinymce-0.6.dist-info/LICENSE
lektor_tinymce-0.6.dist-info/METADATA
lektor_tinymce-0.6.dist-info/WHEEL
lektor_tinymce-0.6.dist-info/entry_points.txt
lektor_tinymce-0.6.dist-info/top_level.txt
lektor_tinymce-0.6.dist-info/RECORD
