Metadata-Version: 2.1
Name: lektor-tinymce
Version: 0.6
Summary: Lektor Plugin for TinyMCE Text Editor use.
Author: Grigory Vartanyan
Author-email: gvartanyan@spherical.pm
License: MIT
Keywords: lektor,plugin,tinymce,rich-text,editor,wysiwyg
Classifier: Framework :: Lektor
Classifier: Environment :: Plugins
License-File: LICENSE
Requires-Dist: lektor <3.4,>=3.3.6
